huey_monitor/__init__.py
huey_monitor/admin.py
huey_monitor/apps.py
huey_monitor/checks.py
huey_monitor/constants.py
huey_monitor/context_processors.py
huey_monitor/exceptions.py
huey_monitor/humanize.py
huey_monitor/models.py
huey_monitor/tasks.py
huey_monitor/tqdm.py
huey_monitor/locale/de/LC_MESSAGES/django.mo
huey_monitor/locale/de/LC_MESSAGES/django.po
huey_monitor/locale/en/LC_MESSAGES/django.mo
huey_monitor/locale/en/LC_MESSAGES/django.po
huey_monitor/migrations/0001_initial.py
huey_monitor/migrations/0002_fix_delete.py
huey_monitor/migrations/0003_add_meta_fields.py
huey_monitor/migrations/0004_add_parent_task_relation.py
huey_monitor/migrations/0005_progress_info.py
huey_monitor/migrations/0006_add_progress_count.py
huey_monitor/migrations/0007_data_migration.py
huey_monitor/migrations/0008_delete_taskprogressmodel.py
huey_monitor/migrations/0009_fix_optinal_fields.py
huey_monitor/migrations/0010_alter_taskmodel_parent_task.py
huey_monitor/migrations/0011_remove_taskmodel_parent_task_remove_taskmodel_state_and_more.py
huey_monitor/migrations/0012_initial.py
huey_monitor/migrations/__init__.py
huey_monitor/static/huey_monitor.css
huey_monitor/templates/admin/huey_monitor/huey_counts_info.html
huey_monitor/templates/admin/huey_monitor/taskmodel/change_list.html
huey_monitor/templates/admin/huey_monitor/taskmodel/change_list_object_tools.html
huey_monitor/templates/admin/huey_monitor/taskmodel/column_name.html
huey_monitor/templates/admin/huey_monitor/taskmodel/field_signals.html
huey_monitor/templates/admin/huey_monitor/taskmodel/task_hierarchy_info.html
huey_monitor/templatetags/__init__.py
huey_monitor/templatetags/huey_monitor.py
huey_monitor_project/__init__.py
huey_monitor_project/__main__.py
huey_monitor_project/huey_docker_instance.py
huey_monitor_project/huey_tests_instance.py
huey_monitor_project/middlewares.py
huey_monitor_project/urls.py
huey_monitor_project/wsgi.py
huey_monitor_project/settings/__init__.py
huey_monitor_project/settings/docker.py
django_huey_monitor-0.10.1.dist-info/METADATA
django_huey_monitor-0.10.1.dist-info/WHEEL
django_huey_monitor-0.10.1.dist-info/entry_points.txt
django_huey_monitor-0.10.1.dist-info/licenses/LICENSE
django_huey_monitor-0.10.1.dist-info/RECORD
