Metadata-Version: 2.4
Name: django-huey-monitor
Version: 0.10.1
Summary: Django based tool for monitoring huey task queue: https://github.com/coleifer/huey
Project-URL: Documentation, https://github.com/boxine/django-huey-monitor/
Project-URL: Source, https://github.com/boxine/django-huey-monitor/
Author-email: Jens Diemer <django-huey-monitor@jensdiemer.de>
License: GPL-3.0-or-later
License-File: LICENSE
Requires-Python: >=3.11
Requires-Dist: bx-django-utils
Requires-Dist: bx-py-utils
Requires-Dist: django
Requires-Dist: huey
